[
  {
    "word": "ああ",
    "meaning": "Ah!, Oh!",
    "furigana": "ああ"
  },
  {
    "word": "会う",
    "meaning": "to meet, to see",
    "furigana": "あう"
  },
  {
    "word": "青",
    "meaning": "blue",
    "furigana": "あお"
  },
  {
    "word": "青い",
    "meaning": "blue",
    "furigana": "あおい"
  },
  {
    "word": "赤",
    "meaning": "red",
    "furigana": "あか"
  },
  {
    "word": "赤い",
    "meaning": "red",
    "furigana": "あかい"
  },
  {
    "word": "明るい",
    "meaning": "bright (in reference to personality or weather); cheerful",
    "furigana": "あかるい"
  },
  {
    "word": "秋",
    "meaning": "fall (season)",
    "furigana": "あき"
  },
  {
    "word": "開く",
    "meaning": "to open, to become open",
    "furigana": "あく"
  },
  {
    "word": "開ける",
    "meaning": "to open (v.t.)",
    "furigana": "あける"
  },
  {
    "word": "上げる",
    "meaning": "to raise, to lift",
    "furigana": "あげる"
  },
  {
    "word": "朝",
    "meaning": "morning",
    "furigana": "あさ"
  },
  {
    "word": "朝御飯",
    "meaning": "breakfast",
    "furigana": "あさごはん"
  },
  {
    "word": "明後日",
    "meaning": "day after tomorrow",
    "furigana": "あさって"
  },
  {
    "word": "足; 脚",
    "meaning": "foot; leg",
    "furigana": "あし"
  },
  {
    "word": "明日",
    "meaning": "tomorrow",
    "furigana": "あした"
  },
  {
    "word": "あそこ",
    "meaning": "there, over there, that place",
    "furigana": "あそこ"
  },
  {
    "word": "遊ぶ",
    "meaning": "to play; to spend time pleasantly; to hang out",
    "furigana": "あそぶ"
  },
  {
    "word": "暖かい",
    "meaning": "warm",
    "furigana": "あたたかい"
  },
  {
    "word": "頭",
    "meaning": "head",
    "furigana": "あたま"
  },
  {
    "word": "新しい",
    "meaning": "new",
    "furigana": "あたらしい"
  },
  {
    "word": "あちら",
    "meaning": "this way (polite)",
    "furigana": "あちら"
  },
  {
    "word": "暑い",
    "meaning": "hot (in reference to weather), warm",
    "furigana": "あつい"
  },
  {
    "word": "熱い",
    "meaning": "hot (objects)",
    "furigana": "あつい"
  },
  {
    "word": "厚い",
    "meaning": "kind, warm(hearted), thick, deep",
    "furigana": "あつい"
  },
  {
    "word": "あっち",
    "meaning": "over there",
    "furigana": "あっち"
  },
  {
    "word": "後",
    "meaning": "afterwards (later); in the future; the rest; since then",
    "furigana": "あと"
  },
  {
    "word": "あなた",
    "meaning": "you",
    "furigana": "あなた"
  },
  {
    "word": "兄",
    "meaning": "(my) older brother (humble)",
    "furigana": "あに"
  },
  {
    "word": "姉",
    "meaning": "(my) older sister (humble)",
    "furigana": "あね"
  },
  {
    "word": "アパート",
    "meaning": "apartment (abbr.)",
    "furigana": "アパート"
  },
  {
    "word": "あの",
    "meaning": "that over there; like that, that way; um...",
    "furigana": "あの"
  },
  {
    "word": "浴びる",
    "meaning": "to bathe, to shower",
    "furigana": "あびる"
  },
  {
    "word": "危ない",
    "meaning": "dangerous, critical",
    "furigana": "あぶない"
  },
  {
    "word": "甘い",
    "meaning": "generous, sweet",
    "furigana": "あまい"
  },
  {
    "word": "余り",
    "meaning": "not very; surplus",
    "furigana": "あまり"
  },
  {
    "word": "雨",
    "meaning": "rain",
    "furigana": "あめ"
  },
  {
    "word": "飴",
    "meaning": "(hard) candy",
    "furigana": "あめ"
  },
  {
    "word": "洗う",
    "meaning": "to wash",
    "furigana": "あらう"
  },
  {
    "word": "在る",
    "meaning": "to be, to have",
    "furigana": "ある"
  },
  {
    "word": "有る",
    "meaning": "to be, to have",
    "furigana": "ある"
  },
  {
    "word": "歩く",
    "meaning": "to walk",
    "furigana": "あるく"
  },
  {
    "word": "あれ",
    "meaning": "that one (over there)",
    "furigana": "あれ"
  },
  {
    "word": "いい; よい",
    "meaning": "good",
    "furigana": "いい; よい"
  },
  {
    "word": "いいえ",
    "meaning": "no, not at all",
    "furigana": "いいえ"
  },
  {
    "word": "言う",
    "meaning": "to say",
    "furigana": "いう"
  },
  {
    "word": "家",
    "meaning": "house, home",
    "furigana": "いえ"
  },
  {
    "word": "いかが",
    "meaning": "how, in what way",
    "furigana": "いかが"
  },
  {
    "word": "行く",
    "meaning": "to go",
    "furigana": "いく; ゆく"
  },
  {
    "word": "いくつ",
    "meaning": "how many, how old",
    "furigana": "いくつ"
  },
  {
    "word": "いくら",
    "meaning": "how much, how many",
    "furigana": "いくら"
  },
  {
    "word": "池",
    "meaning": "pond",
    "furigana": "いけ"
  },
  {
    "word": "医者",
    "meaning": "doctor; physician",
    "furigana": "いしゃ"
  },
  {
    "word": "椅子",
    "meaning": "chair",
    "furigana": "いす"
  },
  {
    "word": "忙しい",
    "meaning": "busy (people, days)",
    "furigana": "いそがしい"
  },
  {
    "word": "痛い",
    "meaning": "hurt; painful; sore",
    "furigana": "いたい"
  },
  {
    "word": "一",
    "meaning": "one",
    "furigana": "いち"
  },
  {
    "word": "一日",
    "meaning": "one day (duration)",
    "furigana": "いちにち"
  },
  {
    "word": "一番",
    "meaning": "best (most), first, number one",
    "furigana": "いちばん"
  },
  {
    "word": "いつ",
    "meaning": "when",
    "furigana": "いつ"
  },
  {
    "word": "五日",
    "meaning": "five days; fifth day of the month",
    "furigana": "いつか"
  },
  {
    "word": "一緒",
    "meaning": "together",
    "furigana": "いっしょ"
  },
  {
    "word": "五つ",
    "meaning": "five things",
    "furigana": "いつつ"
  },
  {
    "word": "いつも",
    "meaning": "always, usually, every time, never (with neg. verb)",
    "furigana": "いつも"
  },
  {
    "word": "犬",
    "meaning": "dog",
    "furigana": "いぬ"
  },
  {
    "word": "今",
    "meaning": "now",
    "furigana": "いま"
  },
  {
    "word": "意味",
    "meaning": "meaning, significance",
    "furigana": "いみ"
  },
  {
    "word": "妹",
    "meaning": "younger sister (humble)",
    "furigana": "いもうと"
  },
  {
    "word": "嫌",
    "meaning": "disagreeable, detestable, unpleasant",
    "furigana": "いや"
  },
  {
    "word": "入口",
    "meaning": "entrance",
    "furigana": "いりぐち"
  },
  {
    "word": "居る",
    "meaning": "(humble) to be (animate), to exist",
    "furigana": "いる"
  },
  {
    "word": "要る",
    "meaning": "to need",
    "furigana": "いる"
  },
  {
    "word": "入れる",
    "meaning": "to put in",
    "furigana": "いれる"
  },
  {
    "word": "色",
    "meaning": "color",
    "furigana": "いろ"
  },
  {
    "word": "色々",
    "meaning": "various",
    "furigana": "いろいろ"
  },
  {
    "word": "上",
    "meaning": "above (up, top, etc.), over, on top of",
    "furigana": "うえ"
  },
  {
    "word": "後ろ",
    "meaning": "back, behind, rear",
    "furigana": "うしろ"
  },
  {
    "word": "薄い",
    "meaning": "thin, weak",
    "furigana": "うすい"
  },
  {
    "word": "歌",
    "meaning": "a song",
    "furigana": "うた"
  },
  {
    "word": "歌う",
    "meaning": "to sing",
    "furigana": "うたう"
  },
  {
    "word": "うち",
    "meaning": "home; house; my place",
    "furigana": "うち"
  },
  {
    "word": "生まれる",
    "meaning": "to be born",
    "furigana": "うまれる"
  },
  {
    "word": "海",
    "meaning": "sea, beach",
    "furigana": "うみ"
  },
  {
    "word": "売る",
    "meaning": "to sell (v.t.)",
    "furigana": "うる"
  },
  {
    "word": "うるさい",
    "meaning": "noisy; annoying",
    "furigana": "うるさい"
  },
  {
    "word": "上着",
    "meaning": "coat, jacket",
    "furigana": "うわぎ"
  },
  {
    "word": "絵",
    "meaning": "a painting; a picture; a drawing",
    "furigana": "え"
  },
  {
    "word": "映画",
    "meaning": "movie, film",
    "furigana": "えいが"
  },
  {
    "word": "映画館",
    "meaning": "movie theater, cinema",
    "furigana": "えいがかん"
  },
  {
    "word": "英語",
    "meaning": "English (language)",
    "furigana": "えいご"
  },
  {
    "word": "ええ",
    "meaning": "yes",
    "furigana": "ええ"
  },
  {
    "word": "駅",
    "meaning": "station",
    "furigana": "えき"
  },
  {
    "word": "エレベーター",
    "meaning": "elevator",
    "furigana": "エレベーター"
  },
  {
    "word": "～円",
    "meaning": "Yen",
    "furigana": "～えん"
  },
  {
    "word": "鉛筆",
    "meaning": "pencil",
    "furigana": "えんぴつ"
  },
  {
    "word": "お～",
    "meaning": "honorable ~ (honorific)",
    "furigana": "お～"
  },
  {
    "word": "美味しい",
    "meaning": "delicious, tasty",
    "furigana": "おいしい"
  },
  {
    "word": "多い",
    "meaning": "many; there are a lot",
    "furigana": "おおい"
  },
  {
    "word": "大きい",
    "meaning": "big, large",
    "furigana": "おおきい"
  },
  {
    "word": "大きな",
    "meaning": "big",
    "furigana": "おおきな"
  },
  {
    "word": "大勢",
    "meaning": "great number of people",
    "furigana": "おおぜい"
  },
  {
    "word": "お母さん",
    "meaning": "mother (formal)",
    "furigana": "おかあさん"
  },
  {
    "word": "お菓子",
    "meaning": "confections, sweets, snack",
    "furigana": "おかし"
  },
  {
    "word": "お金",
    "meaning": "money",
    "furigana": "おかね"
  },
  {
    "word": "起きる",
    "meaning": "to get up (e.g., from sleeping); to happen",
    "furigana": "おきる"
  },
  {
    "word": "置く",
    "meaning": "to put; to lay; to place",
    "furigana": "おく"
  },
  {
    "word": "奥さん",
    "meaning": "(someone else's) wife (hon.)",
    "furigana": "おくさん"
  },
  {
    "word": "お酒",
    "meaning": "sake; alcohol",
    "furigana": "おさけ"
  },
  {
    "word": "お皿",
    "meaning": "plate, dish",
    "furigana": "おさら"
  },
  {
    "word": "伯父; 叔父さん",
    "meaning": "uncle, middle-aged man",
    "furigana": "おじさん"
  },
  {
    "word": "おじいさん",
    "meaning": "grandfather, male senior citizen",
    "furigana": "おじいさん"
  },
  {
    "word": "教える",
    "meaning": "to teach, to inform, to instruct",
    "furigana": "おしえる"
  },
  {
    "word": "押す",
    "meaning": "to push, to press, to stamp (e.g., a passport)",
    "furigana": "おす"
  },
  {
    "word": "遅い",
    "meaning": "slow; (to be) late",
    "furigana": "おそい"
  },
  {
    "word": "お茶",
    "meaning": "(green) tea",
    "furigana": "おちゃ"
  },
  {
    "word": "お手洗い",
    "meaning": "toilet, restroom, bathroom (lit., a place to wash one's hands)",
    "furigana": "おてあらい"
  },
  {
    "word": "お父さん",
    "meaning": "father (formal)",
    "furigana": "おとうさん"
  },
  {
    "word": "弟",
    "meaning": "younger brother",
    "furigana": "おとうと"
  },
  {
    "word": "男",
    "meaning": "man, male",
    "furigana": "おとこ"
  },
  {
    "word": "男の子",
    "meaning": "boy",
    "furigana": "おとこのこ"
  },
  {
    "word": "一昨日",
    "meaning": "the day before yesterday",
    "furigana": "おととい"
  },
  {
    "word": "おととし",
    "meaning": "year before last",
    "furigana": "おととし"
  },
  {
    "word": "大人",
    "meaning": "adult",
    "furigana": "おとな"
  },
  {
    "word": "お腹",
    "meaning": "stomach",
    "furigana": "おなか"
  },
  {
    "word": "同じ",
    "meaning": "same, identical",
    "furigana": "おなじ"
  },
  {
    "word": "お兄さん",
    "meaning": "(someone else's) older brother (formal)",
    "furigana": "おにいさん"
  },
  {
    "word": "お姉さん",
    "meaning": "older sister (formal)",
    "furigana": "おねえさん"
  },
  {
    "word": "伯母さん; 叔母さん",
    "meaning": "aunt",
    "furigana": "おばさん"
  },
  {
    "word": "おばあさん",
    "meaning": "grandmother, female senior-citizen",
    "furigana": "おばあさん"
  },
  {
    "word": "お風呂",
    "meaning": "a bath",
    "furigana": "おふろ"
  },
  {
    "word": "お弁当",
    "meaning": "a boxed lunch",
    "furigana": "おべんとう"
  },
  {
    "word": "覚える",
    "meaning": "to learn, to commit to memory, to remember, to memorize",
    "furigana": "おぼえる"
  },
  {
    "word": "おまわりさん",
    "meaning": "policeman (friendly term)",
    "furigana": "おまわりさん"
  },
  {
    "word": "重い",
    "meaning": "heavy; serious",
    "furigana": "おもい"
  },
  {
    "word": "面白い",
    "meaning": "interesting, amusing",
    "furigana": "おもしろい"
  },
  {
    "word": "泳ぐ",
    "meaning": "to swim",
    "furigana": "およぐ"
  },
  {
    "word": "降りる",
    "meaning": "to get off",
    "furigana": "おりる"
  },
  {
    "word": "終る",
    "meaning": "to finish, to close",
    "furigana": "おわる"
  },
  {
    "word": "音楽",
    "meaning": "Music",
    "furigana": "おんがく"
  },
  {
    "word": "女",
    "meaning": "woman, female",
    "furigana": "おんな"
  },
  {
    "word": "女の子",
    "meaning": "girl",
    "furigana": "おんなのこ"
  },
  {
    "word": "～回",
    "meaning": "counter for occurrences (~ times)",
    "furigana": "～かい"
  },
  {
    "word": "～階",
    "meaning": "counter for stories (floors) of a building",
    "furigana": "～かい"
  },
  {
    "word": "外国",
    "meaning": "foreign country; abroad",
    "furigana": "がいこく"
  },
  {
    "word": "外国人",
    "meaning": "foreigner",
    "furigana": "がいこくじん"
  },
  {
    "word": "会社",
    "meaning": "company, corporation",
    "furigana": "かいしゃ"
  },
  {
    "word": "階段",
    "meaning": "stairs",
    "furigana": "かいだん"
  },
  {
    "word": "買い物",
    "meaning": "shopping",
    "furigana": "かいもの"
  },
  {
    "word": "買う",
    "meaning": "to buy",
    "furigana": "かう"
  },
  {
    "word": "返す",
    "meaning": "to return something",
    "furigana": "かえす"
  },
  {
    "word": "帰る",
    "meaning": "to go back, to go home, to return",
    "furigana": "かえる"
  },
  {
    "word": "顔",
    "meaning": "face (body part)",
    "furigana": "かお"
  },
  {
    "word": "かかる",
    "meaning": "it takes (amount of time, money) (v.i.)",
    "furigana": "かかる"
  },
  {
    "word": "鍵",
    "meaning": "a lock; a key",
    "furigana": "かぎ"
  },
  {
    "word": "書く",
    "meaning": "to write",
    "furigana": "かく"
  },
  {
    "word": "学生",
    "meaning": "student",
    "furigana": "がくせい"
  },
  {
    "word": "～か月",
    "meaning": "(number of) months",
    "furigana": "～かげつ"
  },
  {
    "word": "掛ける",
    "meaning": "to put on (e.g., glasses); to hang (e.g., on a wall)",
    "furigana": "かける"
  },
  {
    "word": "かける",
    "meaning": "to dial/call (e.g., phone); to sit down",
    "furigana": "かける"
  },
  {
    "word": "傘",
    "meaning": "umbrella, parasol",
    "furigana": "かさ"
  },
  {
    "word": "貸す",
    "meaning": "to lend",
    "furigana": "かす"
  },
  {
    "word": "風",
    "meaning": "wind, breeze",
    "furigana": "かぜ"
  },
  {
    "word": "風邪",
    "meaning": "cold, flu",
    "furigana": "かぜ"
  },
  {
    "word": "方",
    "meaning": "-- honorific form for 人 (ひと) --; way of doing",
    "furigana": "かた"
  },
  {
    "word": "家族",
    "meaning": "family, members of a family",
    "furigana": "かぞく"
  },
  {
    "word": "片仮名",
    "meaning": "katakana",
    "furigana": "かたかな"
  },
  {
    "word": "～月",
    "meaning": "month of year",
    "furigana": "～がつ"
  },
  {
    "word": "学校",
    "meaning": "a school",
    "furigana": "がっこう"
  },
  {
    "word": "カップ",
    "meaning": "cup",
    "furigana": "カップ"
  },
  {
    "word": "家庭",
    "meaning": "home; family",
    "furigana": "かてい"
  },
  {
    "word": "角",
    "meaning": "corner (e.g., desk, pavement)",
    "furigana": "かど"
  },
  {
    "word": "かばん",
    "meaning": "bag, basket",
    "furigana": "かばん"
  },
  {
    "word": "花瓶",
    "meaning": "(flower) vase",
    "furigana": "かびん"
  },
  {
    "word": "かぶる",
    "meaning": "to wear, to put on (e.g., a hat on the head)",
    "furigana": "かぶる"
  },
  {
    "word": "紙",
    "meaning": "paper",
    "furigana": "かみ"
  },
  {
    "word": "カメラ",
    "meaning": "camera",
    "furigana": "カメラ"
  },
  {
    "word": "火曜日",
    "meaning": "Tuesday",
    "furigana": "かようび"
  },
  {
    "word": "辛い",
    "meaning": "hot and spicy; salty",
    "furigana": "からい"
  },
  {
    "word": "体",
    "meaning": "body; health",
    "furigana": "からだ"
  },
  {
    "word": "借りる",
    "meaning": "to borrow, to owe",
    "furigana": "かりる"
  },
  {
    "word": "～がる",
    "meaning": "feel",
    "furigana": "～がる"
  },
  {
    "word": "軽い",
    "meaning": "light, non-serious, minor",
    "furigana": "かるい"
  },
  {
    "word": "カレー",
    "meaning": "curry (abbr. for curry and rice)",
    "furigana": "カレー"
  },
  {
    "word": "カレンダー",
    "meaning": "calendar",
    "furigana": "カレンダー"
  },
  {
    "word": "川; 河",
    "meaning": "river",
    "furigana": "かわ"
  },
  {
    "word": "～側",
    "meaning": "~ side",
    "furigana": "～がわ"
  },
  {
    "word": "可愛い",
    "meaning": "cute, adorable",
    "furigana": "かわいい"
  },
  {
    "word": "漢字",
    "meaning": "kanji; Chinese character",
    "furigana": "かんじ"
  },
  {
    "word": "木",
    "meaning": "tree, wood, timber",
    "furigana": "き"
  },
  {
    "word": "黄色",
    "meaning": "yellow",
    "furigana": "きいろ"
  },
  {
    "word": "黄色い",
    "meaning": "yellow",
    "furigana": "きいろい"
  },
  {
    "word": "消える",
    "meaning": "to vanish, to disappear",
    "furigana": "きえる"
  },
  {
    "word": "聞く",
    "meaning": "to hear, to listen, to ask",
    "furigana": "きく"
  },
  {
    "word": "北",
    "meaning": "north",
    "furigana": "きた"
  },
  {
    "word": "ギター",
    "meaning": "guitar",
    "furigana": "ギター"
  },
  {
    "word": "汚い",
    "meaning": "dirty, unclean, filthy",
    "furigana": "きたない"
  },
  {
    "word": "喫茶店",
    "meaning": "café",
    "furigana": "きっさてん"
  },
  {
    "word": "切手",
    "meaning": "postal (postage) stamps",
    "furigana": "きって"
  },
  {
    "word": "切符",
    "meaning": "a ticket",
    "furigana": "きっぷ"
  },
  {
    "word": "昨日",
    "meaning": "yesterday",
    "furigana": "きのう"
  },
  {
    "word": "九",
    "meaning": "nine",
    "furigana": "きゅう"
  },
  {
    "word": "牛肉",
    "meaning": "beef",
    "furigana": "ぎゅうにく"
  },
  {
    "word": "牛乳",
    "meaning": "milk",
    "furigana": "ぎゅうにゅう"
  },
  {
    "word": "今日",
    "meaning": "today, this day",
    "furigana": "きょう"
  },
  {
    "word": "教室",
    "meaning": "classroom",
    "furigana": "きょうしつ"
  },
  {
    "word": "兄弟",
    "meaning": "siblings (humble), brothers and sisters",
    "furigana": "きょうだい"
  },
  {
    "word": "去年",
    "meaning": "last year",
    "furigana": "きょねん"
  },
  {
    "word": "嫌い",
    "meaning": "dislike",
    "furigana": "きらい"
  },
  {
    "word": "切る",
    "meaning": "to cut; to hang up (a phone)",
    "furigana": "きる"
  },
  {
    "word": "着る",
    "meaning": "to put on (clothes above your waist); to wear",
    "furigana": "きる"
  },
  {
    "word": "綺麗",
    "meaning": "pretty, clean, tidy",
    "furigana": "きれい"
  },
  {
    "word": "キロ; キログラム",
    "meaning": "(abbr.) kilo (kilogram)",
    "furigana": "キロ; キログラム"
  },
  {
    "word": "キロ; キロメートル",
    "meaning": "(abbr.) kilo (kilometer)",
    "furigana": "キロ; キロメートル"
  },
  {
    "word": "銀行",
    "meaning": "bank",
    "furigana": "ぎんこう"
  },
  {
    "word": "金曜日",
    "meaning": "Friday",
    "furigana": "きんようび"
  },
  {
    "word": "九",
    "meaning": "nine",
    "furigana": "く"
  },
  {
    "word": "薬",
    "meaning": "medicine",
    "furigana": "くすり"
  },
  {
    "word": "下さい",
    "meaning": "(with te-form verb) please do for me",
    "furigana": "ください"
  },
  {
    "word": "果物",
    "meaning": "fruit",
    "furigana": "くだもの"
  },
  {
    "word": "口",
    "meaning": "job opening; mouth",
    "furigana": "くち"
  },
  {
    "word": "靴",
    "meaning": "shoes, footwear",
    "furigana": "くつ"
  },
  {
    "word": "靴下",
    "meaning": "socks",
    "furigana": "くつした"
  },
  {
    "word": "国",
    "meaning": "country; place of origin",
    "furigana": "くに"
  },
  {
    "word": "曇り",
    "meaning": "cloudiness, cloudy weather",
    "furigana": "くもり"
  },
  {
    "word": "曇る",
    "meaning": "to become cloudy, to become dim",
    "furigana": "くもる"
  },
  {
    "word": "暗い",
    "meaning": "dark, gloomy",
    "furigana": "くらい"
  },
  {
    "word": "～くらい; ぐらい",
    "meaning": "approximate (quantity)",
    "furigana": "～くらい; ぐらい"
  },
  {
    "word": "クラス",
    "meaning": "a class",
    "furigana": "クラス"
  },
  {
    "word": "グラム",
    "meaning": "gram",
    "furigana": "グラム"
  },
  {
    "word": "来る",
    "meaning": "to come",
    "furigana": "くる"
  },
  {
    "word": "車",
    "meaning": "car, vehicle",
    "furigana": "くるま"
  },
  {
    "word": "黒",
    "meaning": "black",
    "furigana": "くろ"
  },
  {
    "word": "黒い",
    "meaning": "black; dark",
    "furigana": "くろい"
  },
  {
    "word": "警官",
    "meaning": "police officer",
    "furigana": "けいかん"
  },
  {
    "word": "今朝",
    "meaning": "this morning",
    "furigana": "けさ"
  },
  {
    "word": "消す",
    "meaning": "to erase, to delete, to turn off power",
    "furigana": "けす"
  },
  {
    "word": "結構",
    "meaning": "splendid; enough, tolerably",
    "furigana": "けっこう"
  },
  {
    "word": "結婚",
    "meaning": "marriage (get married)",
    "furigana": "けっこん (する)"
  },
  {
    "word": "月曜日",
    "meaning": "Monday",
    "furigana": "げつようび"
  },
  {
    "word": "玄関",
    "meaning": "entrance (to a house or a building)",
    "furigana": "げんかん"
  },
  {
    "word": "元気",
    "meaning": "health(y), energetic",
    "furigana": "げんき"
  },
  {
    "word": "～個",
    "meaning": "counter for small items (e.g., fruits, cups)",
    "furigana": "～こ"
  },
  {
    "word": "五",
    "meaning": "five",
    "furigana": "ご"
  },
  {
    "word": "～語",
    "meaning": "word, language",
    "furigana": "～ご"
  },
  {
    "word": "公園",
    "meaning": "a park",
    "furigana": "こうえん"
  },
  {
    "word": "交差点",
    "meaning": "intersection",
    "furigana": "こうさてん"
  },
  {
    "word": "紅茶",
    "meaning": "black tea",
    "furigana": "こうちゃ"
  },
  {
    "word": "交番",
    "meaning": "police box",
    "furigana": "こうばん"
  },
  {
    "word": "声",
    "meaning": "voice",
    "furigana": "こえ"
  },
  {
    "word": "コート",
    "meaning": "coat; court (e.g., tennis)",
    "furigana": "コート"
  },
  {
    "word": "コーヒー",
    "meaning": "coffee",
    "furigana": "コーヒー"
  },
  {
    "word": "ここ",
    "meaning": "here, this place",
    "furigana": "ここ"
  },
  {
    "word": "午後",
    "meaning": "afternoon, P.M.",
    "furigana": "ごご"
  },
  {
    "word": "九日",
    "meaning": "nine days; ninth day of the month",
    "furigana": "ここのか"
  },
  {
    "word": "九つ",
    "meaning": "nine things",
    "furigana": "ここのつ"
  },
  {
    "word": "午前",
    "meaning": "morning, A.M.",
    "furigana": "ごぜん"
  },
  {
    "word": "答える",
    "meaning": "to answer, to reply",
    "furigana": "こたえる"
  },
  {
    "word": "こちら",
    "meaning": "this person (polite); this way (polite)",
    "furigana": "こちら"
  },
  {
    "word": "こっち",
    "meaning": "this person; this direction; this side",
    "furigana": "こっち"
  },
  {
    "word": "コップ",
    "meaning": "a tumbler; a glass",
    "furigana": "コップ"
  },
  {
    "word": "今年",
    "meaning": "this year",
    "furigana": "ことし"
  },
  {
    "word": "言葉",
    "meaning": "language; word(s); expression(s)",
    "furigana": "ことば"
  },
  {
    "word": "子供",
    "meaning": "child(ren)",
    "furigana": "こども"
  },
  {
    "word": "この",
    "meaning": "this",
    "furigana": "この"
  },
  {
    "word": "御飯",
    "meaning": "rice (cooked); meal",
    "furigana": "ごはん"
  },
  {
    "word": "コピーする",
    "meaning": "to copy",
    "furigana": "コピーする"
  },
  {
    "word": "困る",
    "meaning": "to be bothered, to have difficulty",
    "furigana": "こまる"
  },
  {
    "word": "これ",
    "meaning": "this one",
    "furigana": "これ"
  },
  {
    "word": "～ころ; ～ごろ",
    "meaning": "about, toward, approximately (time)",
    "furigana": "～ころ; ～ごろ"
  },
  {
    "word": "今月",
    "meaning": "this month",
    "furigana": "こんげつ"
  },
  {
    "word": "今週",
    "meaning": "this week",
    "furigana": "こんしゅう"
  },
  {
    "word": "こんな",
    "meaning": "such, like this",
    "furigana": "こんな"
  },
  {
    "word": "今晩",
    "meaning": "tonight, this evening",
    "furigana": "こんばん"
  },
  {
    "word": "さあ",
    "meaning": "come now, well",
    "furigana": "さあ"
  },
  {
    "word": "～歳",
    "meaning": "~ years old",
    "furigana": "～さい"
  },
  {
    "word": "財布",
    "meaning": "wallet",
    "furigana": "さいふ"
  },
  {
    "word": "魚",
    "meaning": "fish",
    "furigana": "さかな"
  },
  {
    "word": "先",
    "meaning": "future; recent, previous",
    "furigana": "さき"
  },
  {
    "word": "咲く",
    "meaning": "to bloom",
    "furigana": "さく"
  },
  {
    "word": "作文",
    "meaning": "essay; composition",
    "furigana": "さくぶん"
  },
  {
    "word": "差す",
    "meaning": "to raise (stretch out) hands, to raise (e.g., umbrella)",
    "furigana": "さす"
  },
  {
    "word": "～冊",
    "meaning": "counter for books",
    "furigana": "～さつ"
  },
  {
    "word": "雑誌",
    "meaning": "magazine, journal",
    "furigana": "ざっし"
  },
  {
    "word": "砂糖",
    "meaning": "sugar",
    "furigana": "さとう"
  },
  {
    "word": "寒い",
    "meaning": "cold (in reference to weather)",
    "furigana": "さむい"
  },
  {
    "word": "さ来年",
    "meaning": "year after next",
    "furigana": "さらいねん"
  },
  {
    "word": "～さん",
    "meaning": "Mr. ~, Ms. ~",
    "furigana": "～さん"
  },
  {
    "word": "三",
    "meaning": "three",
    "furigana": "さん"
  },
  {
    "word": "散歩",
    "meaning": "walk, stroll",
    "furigana": "さんぽ (する)"
  },
  {
    "word": "四",
    "meaning": "four",
    "furigana": "し"
  },
  {
    "word": "～時",
    "meaning": "~ o'clock (time)",
    "furigana": "～じ"
  },
  {
    "word": "塩",
    "meaning": "salt",
    "furigana": "しお"
  },
  {
    "word": "しかし",
    "meaning": "however; but",
    "furigana": "しかし"
  },
  {
    "word": "時間",
    "meaning": "time",
    "furigana": "じかん"
  },
  {
    "word": "～時間",
    "meaning": "~ hours",
    "furigana": "～じかん"
  },
  {
    "word": "仕事",
    "meaning": "work, job, occupation, employment",
    "furigana": "しごと"
  },
  {
    "word": "辞書",
    "meaning": "dictionary",
    "furigana": "じしょ"
  },
  {
    "word": "静か",
    "meaning": "quiet, calm",
    "furigana": "しずか"
  },
  {
    "word": "下",
    "meaning": "under, below, beneath",
    "furigana": "した"
  },
  {
    "word": "七",
    "meaning": "seven",
    "furigana": "しち"
  },
  {
    "word": "質問",
    "meaning": "question, inquiry",
    "furigana": "しつもん"
  },
  {
    "word": "自転車",
    "meaning": "bicycle",
    "furigana": "じてんしゃ"
  },
  {
    "word": "自動車",
    "meaning": "automobile",
    "furigana": "じどうしゃ"
  },
  {
    "word": "死ぬ",
    "meaning": "to die",
    "furigana": "しぬ"
  },
  {
    "word": "字引",
    "meaning": "dictionary",
    "furigana": "じびき"
  },
  {
    "word": "自分",
    "meaning": "myself, oneself",
    "furigana": "じぶん"
  },
  {
    "word": "閉まる",
    "meaning": "to close, to be closed",
    "furigana": "しまる"
  },
  {
    "word": "閉める",
    "meaning": "to close, to shut",
    "furigana": "しめる"
  },
  {
    "word": "締める",
    "meaning": "to tie, to fasten, to tighten",
    "furigana": "しめる"
  },
  {
    "word": "じゃ; じゃあ",
    "meaning": "well, well then",
    "furigana": "じゃ; じゃあ"
  },
  {
    "word": "写真",
    "meaning": "a picture; a photograph",
    "furigana": "しゃしん"
  },
  {
    "word": "シャツ",
    "meaning": "shirt",
    "furigana": "シャツ"
  },
  {
    "word": "シャワー",
    "meaning": "shower",
    "furigana": "シャワー"
  },
  {
    "word": "十",
    "meaning": "ten",
    "furigana": "じゅう"
  },
  {
    "word": "～中",
    "meaning": "during, while",
    "furigana": "～じゅう"
  },
  {
    "word": "～週間",
    "meaning": "~ weeks",
    "furigana": "～しゅうかん"
  },
  {
    "word": "授業",
    "meaning": "a class (of school)",
    "furigana": "じゅぎょう"
  },
  {
    "word": "宿題",
    "meaning": "homework",
    "furigana": "しゅくだい"
  },
  {
    "word": "上手",
    "meaning": "be good at, skillful",
    "furigana": "じょうず"
  },
  {
    "word": "丈夫",
    "meaning": "strong, solid, durable",
    "furigana": "じょうぶ"
  },
  {
    "word": "醤油",
    "meaning": "soy sauce",
    "furigana": "しょうゆ"
  },
  {
    "word": "食堂",
    "meaning": "cafeteria, dining hall",
    "furigana": "しょくどう"
  },
  {
    "word": "知る",
    "meaning": "to know, to understand",
    "furigana": "しる"
  },
  {
    "word": "白",
    "meaning": "white",
    "furigana": "しろ"
  },
  {
    "word": "白い",
    "meaning": "white",
    "furigana": "しろい"
  },
  {
    "word": "～人",
    "meaning": "counter for people",
    "furigana": "～じん"
  },
  {
    "word": "新聞",
    "meaning": "newspaper",
    "furigana": "しんぶん"
  },
  {
    "word": "水曜日",
    "meaning": "Wednesday",
    "furigana": "すいようび"
  },
  {
    "word": "吸う",
    "meaning": "to breathe in, to suck",
    "furigana": "すう"
  },
  {
    "word": "スカート",
    "meaning": "skirt",
    "furigana": "スカート"
  },
  {
    "word": "好き",
    "meaning": "liking, fondness, love",
    "furigana": "すき"
  },
  {
    "word": "～すぎ",
    "meaning": "past; to exceed, ~ too much",
    "furigana": "～すぎ"
  },
  {
    "word": "少ない",
    "meaning": "a little; a few",
    "furigana": "すくない"
  },
  {
    "word": "すぐに",
    "meaning": "immediately, soon",
    "furigana": "すぐに"
  },
  {
    "word": "少し",
    "meaning": "little, few",
    "furigana": "すこし"
  },
  {
    "word": "涼しい",
    "meaning": "cool, refreshing (in reference to weather)",
    "furigana": "すずしい"
  },
  {
    "word": "～ずつ",
    "meaning": "at a time",
    "furigana": "～ずつ"
  },
  {
    "word": "ストーブ",
    "meaning": "heater (lit: stove)",
    "furigana": "ストーブ"
  },
  {
    "word": "スプーン",
    "meaning": "spoon",
    "furigana": "スプーン"
  },
  {
    "word": "スポーツ",
    "meaning": "sport(s)",
    "furigana": "スポーツ"
  },
  {
    "word": "ズボン",
    "meaning": "trousers",
    "furigana": "ズボン"
  },
  {
    "word": "住む",
    "meaning": "to reside, to live in",
    "furigana": "すむ"
  },
  {
    "word": "する",
    "meaning": "to do, to try; to wear small items (e.g., necktie, watch, etc.)",
    "furigana": "する"
  },
  {
    "word": "座る",
    "meaning": "to sit",
    "furigana": "すわる"
  },
  {
    "word": "背",
    "meaning": "(one's) height, stature",
    "furigana": "せい"
  },
  {
    "word": "生徒",
    "meaning": "student; pupil",
    "furigana": "せいと"
  },
  {
    "word": "セーター",
    "meaning": "sweater",
    "furigana": "セーター"
  },
  {
    "word": "石鹸",
    "meaning": "soap",
    "furigana": "せっけん"
  },
  {
    "word": "背広",
    "meaning": "men's suit",
    "furigana": "せびろ"
  },
  {
    "word": "狭い",
    "meaning": "narrow; not spacious",
    "furigana": "せまい"
  },
  {
    "word": "ゼロ",
    "meaning": "zero",
    "furigana": "ゼロ"
  },
  {
    "word": "千",
    "meaning": "thousand",
    "furigana": "せん"
  },
  {
    "word": "先月",
    "meaning": "last month",
    "furigana": "せんげつ"
  },
  {
    "word": "先週",
    "meaning": "last week",
    "furigana": "せんしゅう"
  },
  {
    "word": "先生",
    "meaning": "teacher, professor; master; doctor",
    "furigana": "せんせい"
  },
  {
    "word": "洗濯",
    "meaning": "washing, laundry",
    "furigana": "せんたく"
  },
  {
    "word": "全部",
    "meaning": "all, entire, whole",
    "furigana": "ぜんぶ"
  },
  {
    "word": "そう; そうです",
    "meaning": "yes; appears, to be the case",
    "furigana": "そう; そうです"
  },
  {
    "word": "掃除",
    "meaning": "cleaning, sweeping",
    "furigana": "そうじ (する)"
  },
  {
    "word": "そうして; そして",
    "meaning": "and, like that",
    "furigana": "そうして; そして"
  },
  {
    "word": "そこ",
    "meaning": "that place, there; bottom, sole",
    "furigana": "そこ"
  },
  {
    "word": "そちら",
    "meaning": "over there",
    "furigana": "そちら"
  },
  {
    "word": "そっち",
    "meaning": "over there",
    "furigana": "そっち"
  },
  {
    "word": "外",
    "meaning": "outside, exterior",
    "furigana": "そと"
  },
  {
    "word": "その",
    "meaning": "that",
    "furigana": "その"
  },
  {
    "word": "そば",
    "meaning": "near, close, beside; Japanese traditional buckwheat noodle",
    "furigana": "そば"
  },
  {
    "word": "空",
    "meaning": "sky",
    "furigana": "そら"
  },
  {
    "word": "それ",
    "meaning": "that one",
    "furigana": "それ"
  },
  {
    "word": "それから",
    "meaning": "and then, after that",
    "furigana": "それから"
  },
  {
    "word": "それでは",
    "meaning": "in that situation, well then...",
    "furigana": "それでは"
  },
  {
    "word": "～台",
    "meaning": "counter for vehicles; machines",
    "furigana": "～だい"
  },
  {
    "word": "大学",
    "meaning": "college; university",
    "furigana": "だいがく"
  },
  {
    "word": "大使館",
    "meaning": "embassy",
    "furigana": "たいしかん"
  },
  {
    "word": "大丈夫",
    "meaning": "It's ok (all right); No need to worry; Everything is under control",
    "furigana": "だいじょうぶ"
  },
  {
    "word": "大好き",
    "meaning": "very like-able, like very much",
    "furigana": "だいすき"
  },
  {
    "word": "大切",
    "meaning": "important",
    "furigana": "たいせつ"
  },
  {
    "word": "台所",
    "meaning": "kitchen",
    "furigana": "だいどころ"
  },
  {
    "word": "大変",
    "meaning": "very; difficult, hard",
    "furigana": "たいへん"
  },
  {
    "word": "高い",
    "meaning": "tall, high; expensive",
    "furigana": "たかい"
  },
  {
    "word": "～だけ",
    "meaning": "only ~, just ~, as ~",
    "furigana": "～だけ"
  },
  {
    "word": "沢山",
    "meaning": "many, much",
    "furigana": "たくさん"
  },
  {
    "word": "タクシー",
    "meaning": "taxi",
    "furigana": "タクシー"
  },
  {
    "word": "出す",
    "meaning": "to take (something) out; to hand in (something)",
    "furigana": "だす"
  },
  {
    "word": "～たち",
    "meaning": "plural suffix",
    "furigana": "～たち"
  },
  {
    "word": "立つ",
    "meaning": "to stand up",
    "furigana": "たつ"
  },
  {
    "word": "たて",
    "meaning": "length, height",
    "furigana": "たて"
  },
  {
    "word": "建物",
    "meaning": "building",
    "furigana": "たてもの"
  },
  {
    "word": "楽しい",
    "meaning": "enjoyable, fun",
    "furigana": "たのしい"
  },
  {
    "word": "頼む",
    "meaning": "to request, to ask (a favor)",
    "furigana": "たのむ"
  },
  {
    "word": "たばこ",
    "meaning": "tobacco, cigarettes",
    "furigana": "たばこ"
  },
  {
    "word": "多分",
    "meaning": "perhaps, probably, maybe",
    "furigana": "たぶん"
  },
  {
    "word": "食べ物",
    "meaning": "food",
    "furigana": "たべもの"
  },
  {
    "word": "食べる",
    "meaning": "to eat",
    "furigana": "たべる"
  },
  {
    "word": "卵",
    "meaning": "egg",
    "furigana": "たまご"
  },
  {
    "word": "誰",
    "meaning": "who",
    "furigana": "だれ"
  },
  {
    "word": "誰か",
    "meaning": "someone",
    "furigana": "だれか"
  },
  {
    "word": "誕生日",
    "meaning": "birthday",
    "furigana": "たんじょうび"
  },
  {
    "word": "段々",
    "meaning": "gradually, by degrees",
    "furigana": "だんだん"
  },
  {
    "word": "小さい",
    "meaning": "small, little",
    "furigana": "ちいさい"
  },
  {
    "word": "小さな",
    "meaning": "small, little",
    "furigana": "ちいさな"
  },
  {
    "word": "近い",
    "meaning": "near, close by, short",
    "furigana": "ちかい"
  },
  {
    "word": "違う",
    "meaning": "to be different; to differ; wrong",
    "furigana": "ちがう"
  },
  {
    "word": "近く",
    "meaning": "nearby; in the neighborhood",
    "furigana": "ちかく"
  },
  {
    "word": "地下鉄",
    "meaning": "underground train, subway",
    "furigana": "ちかてつ"
  },
  {
    "word": "地図",
    "meaning": "a map",
    "furigana": "ちず"
  },
  {
    "word": "父",
    "meaning": "(my) father",
    "furigana": "ちち"
  },
  {
    "word": "茶色",
    "meaning": "brown",
    "furigana": "ちゃいろ"
  },
  {
    "word": "茶碗",
    "meaning": "rice bowl",
    "furigana": "ちゃわん"
  },
  {
    "word": "～中",
    "meaning": "during, while ~ing",
    "furigana": "～ちゅう"
  },
  {
    "word": "丁度",
    "meaning": "just, right, exactly",
    "furigana": "ちょうど"
  },
  {
    "word": "ちょっと",
    "meaning": "a little, somewhat; just a little, somewhat",
    "furigana": "ちょっと"
  },
  {
    "word": "一日",
    "meaning": "one day; first day of the month",
    "furigana": "ついたち"
  },
  {
    "word": "使う",
    "meaning": "to use",
    "furigana": "つかう"
  },
  {
    "word": "疲れる",
    "meaning": "to get (become) tired; to become fatigued",
    "furigana": "つかれる"
  },
  {
    "word": "次",
    "meaning": "next",
    "furigana": "つぎ"
  },
  {
    "word": "着く",
    "meaning": "to arrive at, to reach",
    "furigana": "つく"
  },
  {
    "word": "机",
    "meaning": "desk",
    "furigana": "つくえ"
  },
  {
    "word": "作る",
    "meaning": "to make, to create",
    "furigana": "つくる"
  },
  {
    "word": "つける",
    "meaning": "to turn on (e.g., a light); to take",
    "furigana": "つける"
  },
  {
    "word": "勤める",
    "meaning": "to work (for)",
    "furigana": "つとめる"
  },
  {
    "word": "つまらない",
    "meaning": "boring, dull; insignificant",
    "furigana": "つまらない"
  },
  {
    "word": "冷たい",
    "meaning": "cold (things, people)",
    "furigana": "つめたい"
  },
  {
    "word": "強い",
    "meaning": "strong, powerful",
    "furigana": "つよい"
  },
  {
    "word": "手",
    "meaning": "hand",
    "furigana": "て"
  },
  {
    "word": "テープ",
    "meaning": "tape",
    "furigana": "テープ"
  },
  {
    "word": "テープレコーダー",
    "meaning": "tape recorder",
    "furigana": "テープレコーダー"
  },
  {
    "word": "テーブル",
    "meaning": "table",
    "furigana": "テーブル"
  },
  {
    "word": "出かける",
    "meaning": "to go out; to depart",
    "furigana": "でかける"
  },
  {
    "word": "手紙",
    "meaning": "letter",
    "furigana": "てがみ"
  },
  {
    "word": "できる",
    "meaning": "to be able to (to accomplish)",
    "furigana": "できる"
  },
  {
    "word": "出口",
    "meaning": "an exit",
    "furigana": "でぐち"
  },
  {
    "word": "テスト",
    "meaning": "test",
    "furigana": "テスト"
  },
  {
    "word": "では",
    "meaning": "then, well, so",
    "furigana": "では"
  },
  {
    "word": "デパート",
    "meaning": "(abbr.) department store",
    "furigana": "デパート"
  },
  {
    "word": "でも",
    "meaning": "but, however",
    "furigana": "でも"
  },
  {
    "word": "出る",
    "meaning": "to appear, to leave",
    "furigana": "でる"
  },
  {
    "word": "テレビ",
    "meaning": "television, TV",
    "furigana": "テレビ"
  },
  {
    "word": "天気",
    "meaning": "weather",
    "furigana": "てんき"
  },
  {
    "word": "電気",
    "meaning": "electricity, (electric) light",
    "furigana": "でんき"
  },
  {
    "word": "電車",
    "meaning": "electric train",
    "furigana": "でんしゃ"
  },
  {
    "word": "電話",
    "meaning": "a telephone",
    "furigana": "でんわ"
  },
  {
    "word": "戸",
    "meaning": "door (Japanese style)",
    "furigana": "と"
  },
  {
    "word": "～度",
    "meaning": "counter for occurrences; ~ degree; ~ point",
    "furigana": "～ど"
  },
  {
    "word": "ドア",
    "meaning": "door (Western style)",
    "furigana": "ドア"
  },
  {
    "word": "トイレ",
    "meaning": "bathroom; toilet",
    "furigana": "トイレ"
  },
  {
    "word": "どう",
    "meaning": "how, in what way",
    "furigana": "どう"
  },
  {
    "word": "どうして",
    "meaning": "why, for what reason",
    "furigana": "どうして"
  },
  {
    "word": "どうぞ",
    "meaning": "please, kindly, by all means",
    "furigana": "どうぞ"
  },
  {
    "word": "動物",
    "meaning": "animal",
    "furigana": "どうぶつ"
  },
  {
    "word": "どうも",
    "meaning": "Thank you; somehow; no matter how hard one may try",
    "furigana": "どうも"
  },
  {
    "word": "十",
    "meaning": "ten (~)",
    "furigana": "(〜を) とお"
  },
  {
    "word": "遠い",
    "meaning": "far (away), distant",
    "furigana": "とおい"
  },
  {
    "word": "十日",
    "meaning": "ten days; tenth day of the month",
    "furigana": "とおか"
  },
  {
    "word": "～時",
    "meaning": "at the time of ~",
    "furigana": "～とき"
  },
  {
    "word": "時々",
    "meaning": "sometimes",
    "furigana": "ときどき"
  },
  {
    "word": "時計",
    "meaning": "a watch; a clock",
    "furigana": "とけい"
  },
  {
    "word": "どこ",
    "meaning": "where, what place",
    "furigana": "どこ"
  },
  {
    "word": "所",
    "meaning": "place",
    "furigana": "ところ"
  },
  {
    "word": "年",
    "meaning": "year, age",
    "furigana": "とし"
  },
  {
    "word": "図書館",
    "meaning": "library",
    "furigana": "としょかん"
  },
  {
    "word": "どちら",
    "meaning": "which (one) (way); where (polite)",
    "furigana": "どちら"
  },
  {
    "word": "どっち",
    "meaning": "which one, which way",
    "furigana": "どっち"
  },
  {
    "word": "とても",
    "meaning": "very (much), greatly, exceedingly",
    "furigana": "とても"
  },
  {
    "word": "どなた",
    "meaning": "who",
    "furigana": "どなた"
  },
  {
    "word": "隣",
    "meaning": "next to, next door to",
    "furigana": "となり"
  },
  {
    "word": "どの",
    "meaning": "which",
    "furigana": "どの"
  },
  {
    "word": "飛ぶ",
    "meaning": "to fly, to hop",
    "furigana": "とぶ"
  },
  {
    "word": "止まる",
    "meaning": "to come to a halt",
    "furigana": "とまる"
  },
  {
    "word": "友達",
    "meaning": "friend",
    "furigana": "ともだち"
  },
  {
    "word": "土曜日",
    "meaning": "Saturday",
    "furigana": "どようび"
  },
  {
    "word": "鳥",
    "meaning": "chicken (lit., bird)",
    "furigana": "とり"
  },
  {
    "word": "鶏肉",
    "meaning": "chicken meat",
    "furigana": "とりにく"
  },
  {
    "word": "取る",
    "meaning": "to take (a class); to get (a grade)",
    "furigana": "とる"
  },
  {
    "word": "撮る",
    "meaning": "to take (a photo), to make (a film)",
    "furigana": "とる"
  },
  {
    "word": "どれ",
    "meaning": "which one",
    "furigana": "どれ"
  },
  {
    "word": "どんな",
    "meaning": "what, what kind of",
    "furigana": "どんな"
  },
  {
    "word": "ない",
    "meaning": "there isn't, doesn't have",
    "furigana": "ない"
  },
  {
    "word": "ナイフ",
    "meaning": "knife",
    "furigana": "ナイフ"
  },
  {
    "word": "中",
    "meaning": "inside, middle, among",
    "furigana": "なか"
  },
  {
    "word": "長い",
    "meaning": "long, lengthy",
    "furigana": "ながい"
  },
  {
    "word": "鳴く",
    "meaning": "to make sound (animal)",
    "furigana": "なく"
  },
  {
    "word": "無くす",
    "meaning": "to lose something",
    "furigana": "なくす"
  },
  {
    "word": "なぜ",
    "meaning": "why (same as どうして)",
    "furigana": "なぜ"
  },
  {
    "word": "夏",
    "meaning": "summer",
    "furigana": "なつ"
  },
  {
    "word": "夏休み",
    "meaning": "summer vacation",
    "furigana": "なつやすみ"
  },
  {
    "word": "～など",
    "meaning": "et cetera",
    "furigana": "～など"
  },
  {
    "word": "七つ",
    "meaning": "seven things",
    "furigana": "ななつ"
  },
  {
    "word": "何",
    "meaning": "what",
    "furigana": "なん; なに"
  },
  {
    "word": "七日",
    "meaning": "seven days; seventh day (of the month)",
    "furigana": "なのか"
  },
  {
    "word": "名前",
    "meaning": "name",
    "furigana": "なまえ"
  },
  {
    "word": "習う",
    "meaning": "to learn",
    "furigana": "ならう"
  },
  {
    "word": "並ぶ",
    "meaning": "to line up, to stand in a line (v.i.)",
    "furigana": "ならぶ"
  },
  {
    "word": "並べる",
    "meaning": "to put (things) side by side; to line up",
    "furigana": "ならべる"
  },
  {
    "word": "なる",
    "meaning": "to become",
    "furigana": "なる"
  },
  {
    "word": "何～",
    "meaning": "what sort of ~",
    "furigana": "なん～"
  },
  {
    "word": "二",
    "meaning": "two",
    "furigana": "に"
  },
  {
    "word": "にぎやか",
    "meaning": "bustling, busy",
    "furigana": "にぎやか"
  },
  {
    "word": "肉",
    "meaning": "meat",
    "furigana": "にく"
  },
  {
    "word": "西",
    "meaning": "west",
    "furigana": "にし"
  },
  {
    "word": "～日",
    "meaning": "~ day of the month, for ~ days",
    "furigana": "～にち"
  },
  {
    "word": "日曜日",
    "meaning": "Sunday",
    "furigana": "にちようび"
  },
  {
    "word": "荷物",
    "meaning": "luggage; baggage",
    "furigana": "にもつ"
  },
  {
    "word": "ニュース",
    "meaning": "news",
    "furigana": "ニュース"
  },
  {
    "word": "庭",
    "meaning": "garden",
    "furigana": "にわ"
  },
  {
    "word": "～人",
    "meaning": "counter for people",
    "furigana": "～にん"
  },
  {
    "word": "脱ぐ",
    "meaning": "to take off (clothes)",
    "furigana": "ぬぐ"
  },
  {
    "word": "温い",
    "meaning": "lukewarm",
    "furigana": "ぬるい"
  },
  {
    "word": "ネクタイ",
    "meaning": "tie, necktie",
    "furigana": "ネクタイ"
  },
  {
    "word": "猫",
    "meaning": "cat",
    "furigana": "ねこ"
  },
  {
    "word": "寝る",
    "meaning": "to sleep; to go to sleep; to go to bed",
    "furigana": "ねる"
  },
  {
    "word": "～年",
    "meaning": "~ years",
    "furigana": "～ねん"
  },
  {
    "word": "ノート",
    "meaning": "notebook",
    "furigana": "ノート"
  },
  {
    "word": "登る",
    "meaning": "to climb",
    "furigana": "のぼる"
  },
  {
    "word": "飲み物",
    "meaning": "drink, beverage",
    "furigana": "のみもの"
  },
  {
    "word": "飲む",
    "meaning": "to drink",
    "furigana": "のむ"
  },
  {
    "word": "乗る",
    "meaning": "to get on, to ride in, to board",
    "furigana": "のる"
  },
  {
    "word": "歯",
    "meaning": "tooth",
    "furigana": "は"
  },
  {
    "word": "パーティー",
    "meaning": "a party",
    "furigana": "パーティー"
  },
  {
    "word": "はい",
    "meaning": "yes",
    "furigana": "はい"
  },
  {
    "word": "～杯",
    "meaning": "counter for cupfuls",
    "furigana": "～はい"
  },
  {
    "word": "灰皿",
    "meaning": "ashtray",
    "furigana": "はいざら"
  },
  {
    "word": "入る",
    "meaning": "to enter, to contain, to hold",
    "furigana": "はいる"
  },
  {
    "word": "葉書",
    "meaning": "postcard",
    "furigana": "はがき"
  },
  {
    "word": "はく",
    "meaning": "to put on (items below your waist)",
    "furigana": "はく"
  },
  {
    "word": "箱",
    "meaning": "box",
    "furigana": "はこ"
  },
  {
    "word": "橋",
    "meaning": "bridge",
    "furigana": "はし"
  },
  {
    "word": "箸",
    "meaning": "chopsticks",
    "furigana": "はし"
  },
  {
    "word": "始まる",
    "meaning": "(something) begins",
    "furigana": "はじまる"
  },
  {
    "word": "初め; 始め",
    "meaning": "beginning, start",
    "furigana": "はじめ"
  },
  {
    "word": "初めて",
    "meaning": "for the first time",
    "furigana": "はじめて"
  },
  {
    "word": "走る",
    "meaning": "to run",
    "furigana": "はしる"
  },
  {
    "word": "バス",
    "meaning": "bus; bath; bass",
    "furigana": "バス"
  },
  {
    "word": "バター",
    "meaning": "butter",
    "furigana": "バター"
  },
  {
    "word": "二十歳",
    "meaning": "20 years old",
    "furigana": "はたち"
  },
  {
    "word": "働く",
    "meaning": "to work",
    "furigana": "はたらく"
  },
  {
    "word": "八",
    "meaning": "eight",
    "furigana": "はち"
  },
  {
    "word": "二十日",
    "meaning": "twenty days, twentieth (day of the month)",
    "furigana": "はつか"
  },
  {
    "word": "花",
    "meaning": "flower",
    "furigana": "はな"
  },
  {
    "word": "鼻",
    "meaning": "nose",
    "furigana": "はな"
  },
  {
    "word": "話",
    "meaning": "talk (chat), story",
    "furigana": "はなし"
  },
  {
    "word": "話す",
    "meaning": "to speak",
    "furigana": "はなす"
  },
  {
    "word": "母",
    "meaning": "(my) mother",
    "furigana": "はは"
  },
  {
    "word": "早い",
    "meaning": "early",
    "furigana": "はやい"
  },
  {
    "word": "速い",
    "meaning": "fast, quick",
    "furigana": "はやい"
  },
  {
    "word": "春",
    "meaning": "spring",
    "furigana": "はる"
  },
  {
    "word": "貼る",
    "meaning": "to post; to paste; to attach",
    "furigana": "はる"
  },
  {
    "word": "晴れ",
    "meaning": "clear (sunny) weather",
    "furigana": "はれ"
  },
  {
    "word": "晴れる",
    "meaning": "to be sunny",
    "furigana": "はれる"
  },
  {
    "word": "半",
    "meaning": "half (e.g., にじはん | half-past two)",
    "furigana": "はん"
  },
  {
    "word": "晩",
    "meaning": "evening",
    "furigana": "ばん"
  },
  {
    "word": "～番",
    "meaning": "~st; ~th best",
    "furigana": "～ばん"
  },
  {
    "word": "パン",
    "meaning": "bread",
    "furigana": "パン"
  },
  {
    "word": "ハンカチ",
    "meaning": "handkerchief",
    "furigana": "ハンカチ"
  },
  {
    "word": "番号",
    "meaning": "number, series of digits",
    "furigana": "ばんごう"
  },
  {
    "word": "晩御飯",
    "meaning": "dinner, evening meal",
    "furigana": "ばんごはん"
  },
  {
    "word": "半分",
    "meaning": "half",
    "furigana": "はんぶん"
  },
  {
    "word": "東",
    "meaning": "east",
    "furigana": "ひがし"
  },
  {
    "word": "～匹",
    "meaning": "counter for small animals",
    "furigana": "～ひき"
  },
  {
    "word": "引く",
    "meaning": "to pull, to draw; subtract",
    "furigana": "ひく"
  },
  {
    "word": "弾く",
    "meaning": "to play (a string instrument or piano)",
    "furigana": "ひく"
  },
  {
    "word": "低い",
    "meaning": "short, low",
    "furigana": "ひくい"
  },
  {
    "word": "飛行機",
    "meaning": "airplane",
    "furigana": "ひこうき"
  },
  {
    "word": "左",
    "meaning": "left hand side",
    "furigana": "ひだり"
  },
  {
    "word": "人",
    "meaning": "man, person",
    "furigana": "ひと"
  },
  {
    "word": "一つ",
    "meaning": "one thing",
    "furigana": "ひとつ"
  },
  {
    "word": "一月",
    "meaning": "one month",
    "furigana": "ひとつき"
  },
  {
    "word": "一人",
    "meaning": "one person",
    "furigana": "ひとり"
  },
  {
    "word": "暇",
    "meaning": "free time, leisure",
    "furigana": "ひま"
  },
  {
    "word": "百",
    "meaning": "hundred",
    "furigana": "ひゃく"
  },
  {
    "word": "病院",
    "meaning": "hospital",
    "furigana": "びょういん"
  },
  {
    "word": "病気",
    "meaning": "illness; sickness",
    "furigana": "びょうき"
  },
  {
    "word": "平仮名",
    "meaning": "hiragana",
    "furigana": "ひらがな"
  },
  {
    "word": "昼",
    "meaning": "noon, daytime",
    "furigana": "ひる"
  },
  {
    "word": "昼御飯",
    "meaning": "lunch, midday meal",
    "furigana": "ひるごはん"
  },
  {
    "word": "広い",
    "meaning": "spacious; wide; broad",
    "furigana": "ひろい"
  },
  {
    "word": "フィルム",
    "meaning": "film (roll of)",
    "furigana": "フィルム"
  },
  {
    "word": "封筒",
    "meaning": "envelope",
    "furigana": "ふうとう"
  },
  {
    "word": "プール",
    "meaning": "swimming pool",
    "furigana": "プール"
  },
  {
    "word": "フォーク",
    "meaning": "fork",
    "furigana": "フォーク"
  },
  {
    "word": "吹く",
    "meaning": "to blow (wind, etc.)",
    "furigana": "ふく"
  },
  {
    "word": "服",
    "meaning": "clothes",
    "furigana": "ふく"
  },
  {
    "word": "二つ",
    "meaning": "two things",
    "furigana": "ふたつ"
  },
  {
    "word": "豚肉",
    "meaning": "pork",
    "furigana": "ぶたにく"
  },
  {
    "word": "二人",
    "meaning": "two people",
    "furigana": "ふたり"
  },
  {
    "word": "二日",
    "meaning": "two days; second day of the month",
    "furigana": "ふつか"
  },
  {
    "word": "太い",
    "meaning": "fat, thick",
    "furigana": "ふとい"
  },
  {
    "word": "冬",
    "meaning": "winter",
    "furigana": "ふゆ"
  },
  {
    "word": "降る",
    "meaning": "to precipitate, to fall (e.g., rain, snow, etc.)",
    "furigana": "ふる"
  },
  {
    "word": "古い",
    "meaning": "old (in reference to objects, not people), aged, ancient",
    "furigana": "ふるい"
  },
  {
    "word": "～分",
    "meaning": "~ minutes",
    "furigana": "～ふん"
  },
  {
    "word": "文章",
    "meaning": "sentence, text",
    "furigana": "ぶんしょう"
  },
  {
    "word": "ページ",
    "meaning": "a page",
    "furigana": "ページ"
  },
  {
    "word": "下手",
    "meaning": "unskillful, poor",
    "furigana": "へた"
  },
  {
    "word": "ベッド",
    "meaning": "bed",
    "furigana": "ベッド"
  },
  {
    "word": "ペット",
    "meaning": "pet",
    "furigana": "ペット"
  },
  {
    "word": "部屋",
    "meaning": "a room",
    "furigana": "へや"
  },
  {
    "word": "辺",
    "meaning": "area, vicinity",
    "furigana": "へん"
  },
  {
    "word": "ペン",
    "meaning": "pen",
    "furigana": "ペン"
  },
  {
    "word": "勉強",
    "meaning": "study",
    "furigana": "べんきょう (する)"
  },
  {
    "word": "便利",
    "meaning": "convenient, handy",
    "furigana": "べんり"
  },
  {
    "word": "帽子",
    "meaning": "hat; cap",
    "furigana": "ぼうし"
  },
  {
    "word": "ボールペン",
    "meaning": "ball-point pen",
    "furigana": "ボールペン"
  },
  {
    "word": "外",
    "meaning": "other, the rest",
    "furigana": "ほか"
  },
  {
    "word": "ポケット",
    "meaning": "pocket",
    "furigana": "ポケット"
  },
  {
    "word": "欲しい",
    "meaning": "to want, in need of",
    "furigana": "ほしい"
  },
  {
    "word": "ポスト",
    "meaning": "mailbox; post, position",
    "furigana": "ポスト"
  },
  {
    "word": "細い",
    "meaning": "thin, slender, fine",
    "furigana": "ほそい"
  },
  {
    "word": "ボタン",
    "meaning": "button",
    "furigana": "ボタン"
  },
  {
    "word": "ホテル",
    "meaning": "hotel",
    "furigana": "ホテル"
  },
  {
    "word": "本",
    "meaning": "book",
    "furigana": "ほん"
  },
  {
    "word": "～本",
    "meaning": "counter for long cylindrical things",
    "furigana": "～ほん"
  },
  {
    "word": "本棚",
    "meaning": "bookshelf",
    "furigana": "ほんだな"
  },
  {
    "word": "本当",
    "meaning": "real, true",
    "furigana": "ほんとう"
  },
  {
    "word": "～枚",
    "meaning": "counter for flat things",
    "furigana": "～まい"
  },
  {
    "word": "毎朝",
    "meaning": "every morning",
    "furigana": "まいあさ"
  },
  {
    "word": "毎月",
    "meaning": "every month, monthly",
    "furigana": "まいげつ; まいつき"
  },
  {
    "word": "毎週",
    "meaning": "every week",
    "furigana": "まいしゅう"
  },
  {
    "word": "毎日",
    "meaning": "every day",
    "furigana": "まいにち"
  },
  {
    "word": "毎年",
    "meaning": "every year, yearly, annually",
    "furigana": "まいねん; まいとし"
  },
  {
    "word": "毎晩",
    "meaning": "every night",
    "furigana": "まいばん"
  },
  {
    "word": "前",
    "meaning": "before, in front",
    "furigana": "まえ"
  },
  {
    "word": "～前",
    "meaning": "in front of ~",
    "furigana": "～まえ"
  },
  {
    "word": "曲る",
    "meaning": "to turn, to bend",
    "furigana": "まがる"
  },
  {
    "word": "まずい",
    "meaning": "terrible (in reference to food), unappetizing, unpleasant (taste)",
    "furigana": "まずい"
  },
  {
    "word": "また",
    "meaning": "and; furthermore",
    "furigana": "また"
  },
  {
    "word": "まだ",
    "meaning": "yet, still, besides",
    "furigana": "まだ"
  },
  {
    "word": "町",
    "meaning": "town; city",
    "furigana": "まち"
  },
  {
    "word": "待つ",
    "meaning": "to wait",
    "furigana": "まつ"
  },
  {
    "word": "まっすぐ",
    "meaning": "straight (ahead), direct",
    "furigana": "まっすぐ"
  },
  {
    "word": "マッチ",
    "meaning": "match",
    "furigana": "マッチ"
  },
  {
    "word": "窓",
    "meaning": "window",
    "furigana": "まど"
  },
  {
    "word": "丸い; 円い",
    "meaning": "round, circular",
    "furigana": "まるい"
  },
  {
    "word": "万",
    "meaning": "ten thousand",
    "furigana": "まん"
  },
  {
    "word": "万年筆",
    "meaning": "fountain pen",
    "furigana": "まんねんひつ"
  },
  {
    "word": "磨く",
    "meaning": "to brush (teeth); to polish",
    "furigana": "みがく"
  },
  {
    "word": "右",
    "meaning": "right hand side",
    "furigana": "みぎ"
  },
  {
    "word": "短い",
    "meaning": "short (length)",
    "furigana": "みじかい"
  },
  {
    "word": "水",
    "meaning": "water",
    "furigana": "みず"
  },
  {
    "word": "店",
    "meaning": "store, shop",
    "furigana": "みせ"
  },
  {
    "word": "見せる",
    "meaning": "to show, to display",
    "furigana": "みせる"
  },
  {
    "word": "道",
    "meaning": "road, street; way, directions",
    "furigana": "みち"
  },
  {
    "word": "三日",
    "meaning": "three days, third day of the month",
    "furigana": "みっか"
  },
  {
    "word": "三つ",
    "meaning": "three things",
    "furigana": "みっつ"
  },
  {
    "word": "緑",
    "meaning": "green",
    "furigana": "みどり"
  },
  {
    "word": "皆さん",
    "meaning": "all of you, everyone",
    "furigana": "みなさん"
  },
  {
    "word": "南",
    "meaning": "South",
    "furigana": "みなみ"
  },
  {
    "word": "耳",
    "meaning": "ear",
    "furigana": "みみ"
  },
  {
    "word": "見る",
    "meaning": "to see, to look",
    "furigana": "みる"
  },
  {
    "word": "みんな",
    "meaning": "all, everyone, everybody",
    "furigana": "みんな"
  },
  {
    "word": "六日",
    "meaning": "six days; sixth day of month",
    "furigana": "むいか"
  },
  {
    "word": "向こう",
    "meaning": "beyond, over there",
    "furigana": "むこう"
  },
  {
    "word": "難しい",
    "meaning": "difficult",
    "furigana": "むずかしい"
  },
  {
    "word": "六つ",
    "meaning": "six things",
    "furigana": "むっつ"
  },
  {
    "word": "村",
    "meaning": "village",
    "furigana": "むら"
  },
  {
    "word": "目",
    "meaning": "eye(s)",
    "furigana": "め"
  },
  {
    "word": "メートル",
    "meaning": "meter",
    "furigana": "メートル"
  },
  {
    "word": "眼鏡",
    "meaning": "eye glasses",
    "furigana": "めがね"
  },
  {
    "word": "もう",
    "meaning": "already; again; more",
    "furigana": "もう"
  },
  {
    "word": "木曜日",
    "meaning": "Thursday",
    "furigana": "もくようび"
  },
  {
    "word": "もしもし",
    "meaning": "Hello? (used on the phone)",
    "furigana": "もしもし"
  },
  {
    "word": "持つ",
    "meaning": "to hold, to carry; to possess",
    "furigana": "もつ"
  },
  {
    "word": "もっと",
    "meaning": "more",
    "furigana": "もっと"
  },
  {
    "word": "物",
    "meaning": "thing (concrete object)",
    "furigana": "もの"
  },
  {
    "word": "門",
    "meaning": "gate",
    "furigana": "もん"
  },
  {
    "word": "問題",
    "meaning": "a problem",
    "furigana": "もんだい"
  },
  {
    "word": "～屋",
    "meaning": "~ shop",
    "furigana": "～や"
  },
  {
    "word": "八百屋",
    "meaning": "greengrocer",
    "furigana": "やおや"
  },
  {
    "word": "野菜",
    "meaning": "vegetable",
    "furigana": "やさい"
  },
  {
    "word": "易しい",
    "meaning": "easy, plain, simple",
    "furigana": "やさしい"
  },
  {
    "word": "安い",
    "meaning": "inexpensive; cheap (things)",
    "furigana": "やすい"
  },
  {
    "word": "休み",
    "meaning": "holiday; day off; absence",
    "furigana": "やすみ"
  },
  {
    "word": "休む",
    "meaning": "to rest, to have a break, to get time off",
    "furigana": "やすむ"
  },
  {
    "word": "八つ",
    "meaning": "eight things",
    "furigana": "やっつ"
  },
  {
    "word": "山",
    "meaning": "mountain",
    "furigana": "やま"
  },
  {
    "word": "やる",
    "meaning": "to do; to give (to pets, parents, siblings, etc.)",
    "furigana": "やる"
  },
  {
    "word": "夕方",
    "meaning": "late afternoon (typically just before dinner time), evening",
    "furigana": "ゆうがた"
  },
  {
    "word": "夕飯",
    "meaning": "dinner, supper, evening meal",
    "furigana": "ゆうはん"
  },
  {
    "word": "郵便局",
    "meaning": "post office",
    "furigana": "ゆうびんきょく"
  },
  {
    "word": "昨夜",
    "meaning": "last night",
    "furigana": "ゆうべ"
  },
  {
    "word": "有名",
    "meaning": "famous",
    "furigana": "ゆうめい"
  },
  {
    "word": "雪",
    "meaning": "snow",
    "furigana": "ゆき"
  },
  {
    "word": "ゆっくりと",
    "meaning": "slowly, at ease",
    "furigana": "ゆっくりと"
  },
  {
    "word": "八日",
    "meaning": "eight days; eighth day of the month",
    "furigana": "ようか"
  },
  {
    "word": "洋服",
    "meaning": "Western-style clothes",
    "furigana": "ようふく"
  },
  {
    "word": "よく",
    "meaning": "frequently, often (much); well, skillfully",
    "furigana": "よく"
  },
  {
    "word": "横",
    "meaning": "beside; side; width",
    "furigana": "よこ"
  },
  {
    "word": "四日",
    "meaning": "four days; fourth day of the month",
    "furigana": "よっか"
  },
  {
    "word": "四つ",
    "meaning": "four things",
    "furigana": "よっつ"
  },
  {
    "word": "呼ぶ",
    "meaning": "to call (one's name); to invite",
    "furigana": "よぶ"
  },
  {
    "word": "読む",
    "meaning": "to read",
    "furigana": "よむ"
  },
  {
    "word": "夜",
    "meaning": "evening, night",
    "furigana": "よる"
  },
  {
    "word": "弱い",
    "meaning": "weak",
    "furigana": "よわい"
  },
  {
    "word": "来月",
    "meaning": "next month",
    "furigana": "らいげつ"
  },
  {
    "word": "来週",
    "meaning": "next week",
    "furigana": "らいしゅう"
  },
  {
    "word": "来年",
    "meaning": "next year",
    "furigana": "らいねん"
  },
  {
    "word": "ラジオ",
    "meaning": "radio",
    "furigana": "ラジオ"
  },
  {
    "word": "ラジオカセ",
    "meaning": "radio cassette player",
    "furigana": "ラジオカセ"
  },
  {
    "word": "りっぱ",
    "meaning": "splendid, fine",
    "furigana": "りっぱ"
  },
  {
    "word": "留学生",
    "meaning": "international student",
    "furigana": "りゅうがくせい"
  },
  {
    "word": "両親",
    "meaning": "parents (lit., both parents)",
    "furigana": "りょうしん"
  },
  {
    "word": "料理",
    "meaning": "cooking; cuisine",
    "furigana": "りょうり"
  },
  {
    "word": "旅行",
    "meaning": "travel, trip",
    "furigana": "りょこう"
  },
  {
    "word": "零",
    "meaning": "zero, nought",
    "furigana": "れい"
  },
  {
    "word": "冷蔵庫",
    "meaning": "refrigerator",
    "furigana": "れいぞうこ"
  },
  {
    "word": "レコード",
    "meaning": "record",
    "furigana": "レコード"
  },
  {
    "word": "レストラン",
    "meaning": "restaurant",
    "furigana": "レストラン"
  },
  {
    "word": "練習",
    "meaning": "(to) practice",
    "furigana": "れんしゅう (する)"
  },
  {
    "word": "廊下",
    "meaning": "corridor",
    "furigana": "ろうか"
  },
  {
    "word": "六",
    "meaning": "six",
    "furigana": "ろく"
  },
  {
    "word": "ワイシャツ",
    "meaning": "shirt (lit: white shirt), business shirt",
    "furigana": "ワイシャツ"
  },
  {
    "word": "若い",
    "meaning": "young",
    "furigana": "わかい"
  },
  {
    "word": "分かる",
    "meaning": "to understand",
    "furigana": "わかる"
  },
  {
    "word": "忘れる",
    "meaning": "to forget",
    "furigana": "わすれる"
  },
  {
    "word": "私",
    "meaning": "I, myself",
    "furigana": "わたし"
  },
  {
    "word": "私",
    "meaning": "I (formal), myself, private affairs",
    "furigana": "わたくし"
  },
  {
    "word": "渡す",
    "meaning": "to hand (something) over (v.t.); to get across",
    "furigana": "わたす"
  },
  {
    "word": "渡る",
    "meaning": "to cross over, to go across",
    "furigana": "わたる"
  },
  {
    "word": "悪い",
    "meaning": "bad, sinful; inferior",
    "furigana": "わるい"
  }
]