[
  {
    "word": "方策",
    "meaning_en": "plan; policy",
    "furigana": "ほうさく"
  },
  {
    "word": "上位",
    "meaning_en": "superior (rank not class); higher order (e.g. byte); host computer (of connected device)",
    "furigana": "じょうい"
  },
  {
    "word": "慎む",
    "meaning_en": "to be careful; to be chaste or discreet; to abstain or refrain",
    "furigana": "つつしむ"
  },
  {
    "word": "エンジニア",
    "meaning_en": "engineer",
    "furigana": ""
  },
  {
    "word": "構え",
    "meaning_en": "posture; pose; style",
    "furigana": "かまえ"
  },
  {
    "word": "気楽",
    "meaning_en": "at ease; comfortable",
    "furigana": "きらく"
  },
  {
    "word": "辿り着く",
    "meaning_en": "to grope along to; to struggle on to; to arrive somewhere after a struggle",
    "furigana": "たどりつく"
  },
  {
    "word": "間もなく",
    "meaning_en": "soon; before long; in a short time",
    "furigana": "まもなく"
  },
  {
    "word": "学芸",
    "meaning_en": "arts and sciences; liberal arts",
    "furigana": "がくげい"
  },
  {
    "word": "其れ故",
    "meaning_en": "therefore; for that reason; so",
    "furigana": "それゆえ"
  },
  {
    "word": "差異",
    "meaning_en": "difference; disparity",
    "furigana": "さい"
  },
  {
    "word": "役場",
    "meaning_en": "town hall",
    "furigana": "やくば"
  },
  {
    "word": "ご苦労様",
    "meaning_en": "Thank you very much for your....",
    "furigana": "ごくろうさま"
  },
  {
    "word": "議題",
    "meaning_en": "topic of discussion; agenda",
    "furigana": "ぎだい"
  },
  {
    "word": "保温",
    "meaning_en": "retaining warmth; keeping heat in; heat insulation",
    "furigana": "ほおん"
  },
  {
    "word": "一敗",
    "meaning_en": "one defeat",
    "furigana": "いっぱい"
  },
  {
    "word": "破壊",
    "meaning_en": "destruction",
    "furigana": "はかい"
  },
  {
    "word": "酸化",
    "meaning_en": "oxidation",
    "furigana": "さんか"
  },
  {
    "word": "しまった",
    "meaning_en": "Damn it!",
    "furigana": ""
  },
  {
    "word": "再建",
    "meaning_en": "rebuilding; reconstruction; rehabilitation",
    "furigana": "さいけん"
  },
  {
    "word": "厳か",
    "meaning_en": "austere; majestic; dignified; stately; awful; impressive",
    "furigana": "おごそか"
  },
  {
    "word": "理性",
    "meaning_en": "reason; sense",
    "furigana": "りせい"
  },
  {
    "word": "着飾る",
    "meaning_en": "to dress up",
    "furigana": "きかざる"
  },
  {
    "word": "火花",
    "meaning_en": "spark",
    "furigana": "ひばな"
  },
  {
    "word": "寄贈",
    "meaning_en": "donation; presentation",
    "furigana": "きそう"
  }
]