[
  {
    "word": "難",
    "meaning_en": "difficulty; hardships; defect",
    "furigana": "なん"
  },
  {
    "word": "特産",
    "meaning_en": "specialty; special product",
    "furigana": "とくさん"
  },
  {
    "word": "鋏",
    "meaning_en": "scissors",
    "furigana": "はさみ"
  },
  {
    "word": "指図",
    "meaning_en": "instruction; mandate",
    "furigana": "さしず"
  },
  {
    "word": "履歴",
    "meaning_en": "personal history; background; career; log",
    "furigana": "りれき"
  },
  {
    "word": "敗戦",
    "meaning_en": "defeat; losing a war",
    "furigana": "はいせん"
  },
  {
    "word": "聳える",
    "meaning_en": "to rise; to tower; to soar",
    "furigana": "そびえる"
  },
  {
    "word": "資金",
    "meaning_en": "funds; capital",
    "furigana": "しきん"
  },
  {
    "word": "足し算",
    "meaning_en": "addition",
    "furigana": "たしざん"
  },
  {
    "word": "念",
    "meaning_en": "sense; idea; thought; feeling; desire; concern; attention; care",
    "furigana": "ねん"
  },
  {
    "word": "一見",
    "meaning_en": "unfamiliar; never before met",
    "furigana": "いちげん"
  },
  {
    "word": "進路",
    "meaning_en": "course; route",
    "furigana": "しんろ"
  },
  {
    "word": "通",
    "meaning_en": "connoisseur; counter for letters",
    "furigana": "つう"
  },
  {
    "word": "歓声",
    "meaning_en": "cheer; shout of joy",
    "furigana": "かんせい"
  },
  {
    "word": "並列",
    "meaning_en": "arrangement; parallel; abreast",
    "furigana": "へいれつ"
  },
  {
    "word": "望ましい",
    "meaning_en": "desirable; hoped for",
    "furigana": "のぞましい"
  },
  {
    "word": "現場",
    "meaning_en": "actual spot; scene; scene of the crime",
    "furigana": "げんじょう"
  },
  {
    "word": "備え付ける",
    "meaning_en": "to provide; to furnish; to equip; to install",
    "furigana": "そなえつける"
  },
  {
    "word": "日夜",
    "meaning_en": "day and night; always",
    "furigana": "にちや"
  },
  {
    "word": "ベスト",
    "meaning_en": "best; vest",
    "furigana": ""
  },
  {
    "word": "装備",
    "meaning_en": "equipment",
    "furigana": "そうび"
  },
  {
    "word": "云々",
    "meaning_en": "and so on; and so forth; comment",
    "furigana": "うんぬん"
  },
  {
    "word": "敬具",
    "meaning_en": "Sincerely yours",
    "furigana": "けいぐ"
  },
  {
    "word": "まごつく",
    "meaning_en": "to be confused; to be flustered",
    "furigana": ""
  },
  {
    "word": "早急",
    "meaning_en": "urgent",
    "furigana": "さっきゅう"
  }
]