[
  {
    "word": "回転",
    "meaning_en": "rotation, revolution, turning",
    "furigana": "かいてん"
  },
  {
    "word": "じゅうたん",
    "meaning_en": "carpet",
    "furigana": "（カーペット）"
  },
  {
    "word": "一休み",
    "meaning_en": "a rest",
    "furigana": "ひとやすみ"
  },
  {
    "word": "敬う",
    "meaning_en": "to show respect, to honour",
    "furigana": "うやまう"
  },
  {
    "word": "騒がしい",
    "meaning_en": "noisy",
    "furigana": "さわがしい"
  },
  {
    "word": "先祖",
    "meaning_en": "ancestor",
    "furigana": "せんぞ"
  },
  {
    "word": "引越し",
    "meaning_en": "moving (dwelling etc.), changing residence",
    "furigana": "ひっこし"
  },
  {
    "word": "地名",
    "meaning_en": "place name",
    "furigana": "ちめい"
  },
  {
    "word": "電球",
    "meaning_en": "light bulb",
    "furigana": "でんきゅう"
  },
  {
    "word": "破く",
    "meaning_en": "",
    "furigana": "やぶく"
  },
  {
    "word": "いきなり",
    "meaning_en": "(uk) abruptly, suddenly, all of a sudden, without warning",
    "furigana": ""
  },
  {
    "word": "務める",
    "meaning_en": "(1) to serve, to fill a post, to serve under, to work (for)",
    "furigana": "つとめる"
  },
  {
    "word": "くたびれる",
    "meaning_en": "to get tired, to wear out",
    "furigana": ""
  },
  {
    "word": "退ける",
    "meaning_en": "to remove, to take away, to dislodge, to put something out of the way",
    "furigana": "どける"
  },
  {
    "word": "船便",
    "meaning_en": "surface mail (ship)",
    "furigana": "ふなびん"
  },
  {
    "word": "見舞う",
    "meaning_en": "to ask after (health), to visit",
    "furigana": "みまう"
  },
  {
    "word": "やかましい",
    "meaning_en": "(1) noisy, (2) strict, fussy",
    "furigana": ""
  },
  {
    "word": "継続",
    "meaning_en": "continuation",
    "furigana": "けいぞく"
  },
  {
    "word": "属する",
    "meaning_en": "to belong to, to come under, to be affiliated with, to be subject to",
    "furigana": "ぞくする"
  },
  {
    "word": "重力",
    "meaning_en": "gravity",
    "furigana": "じゅうりょく"
  },
  {
    "word": "早速",
    "meaning_en": "at once, immediately, without delay, promptly",
    "furigana": "さっそく"
  },
  {
    "word": "ビニール",
    "meaning_en": "vinyl",
    "furigana": ""
  },
  {
    "word": "脂",
    "meaning_en": "fat, tallow, lard",
    "furigana": "あぶら"
  },
  {
    "word": "児童",
    "meaning_en": "children, juvenile",
    "furigana": "じどう"
  },
  {
    "word": "応援",
    "meaning_en": "aid, assistance, help, reinforcement",
    "furigana": "おうえん"
  }
]